cornstarch/__init__.py
cornstarch/pipeline_template.py
cornstarch/kernel/__init__.py
cornstarch/kernel/attention.py
cornstarch/kernel/bitfield_attention.py
cornstarch/kernel/interface.py
cornstarch/models/__init__.py
cornstarch/models/evaclip/__init__.py
cornstarch/models/evaclip/configuration_evaclip.py
cornstarch/models/evaclip/modeling_evaclip.py
cornstarch/models/intern_vit/__init__.py
cornstarch/models/intern_vit/configuration_intern_vit.py
cornstarch/models/intern_vit/flash_attention.py
cornstarch/models/intern_vit/modeling_intern_vit.py
cornstarch/models/multimodal_language_model/__init__.py
cornstarch/models/multimodal_language_model/configuration_multimodal_language_model.py
cornstarch/models/multimodal_language_model/modeling_multimodal_language_model.py
cornstarch/models/multimodal_language_model/processing_multimodal_language_model.py
cornstarch/plugin/__init__.py
cornstarch/plugin/encoders_colocated_plugin/__init__.py
cornstarch/plugin/encoders_colocated_plugin/encoders_colocated_plugin.py
cornstarch/plugin/encoders_colocated_plugin/encoders_colocated_stage_manager.py
cornstarch/plugin/encoders_colocated_plugin/one_f_one_b.py
cornstarch/plugin/encoders_colocated_plugin/process_group_mesh.py
cornstarch/plugin/encoders_replicated_plugin/__init__.py
cornstarch/plugin/encoders_replicated_plugin/encoders_replicated_plugin.py
cornstarch/plugin/encoders_replicated_plugin/encoders_replicated_stage_manager.py
cornstarch/plugin/encoders_replicated_plugin/process_group_mesh.py
cornstarch/plugin/heterogeneous_parallel_plugin/__init__.py
cornstarch/plugin/heterogeneous_parallel_plugin/heterogeneous_dataloader.py
cornstarch/plugin/heterogeneous_parallel_plugin/heterogeneous_parallel_module.py
cornstarch/plugin/heterogeneous_parallel_plugin/heterogeneous_parallel_plugin.py
cornstarch/plugin/heterogeneous_parallel_plugin/heterogeneous_process_group_mesh.py
cornstarch/plugin/heterogeneous_parallel_plugin/heterogeneous_stage_manager.py
cornstarch-0.0.5.dist-info/LICENSE.txt
cornstarch-0.0.5.dist-info/METADATA
cornstarch-0.0.5.dist-info/WHEEL
cornstarch-0.0.5.dist-info/top_level.txt
cornstarch-0.0.5.dist-info/RECORD
