Metadata-Version: 2.2
Name: cornstarch
Version: 0.0.5
Summary: A multimodal model training toolkit
Author-email: Insu Jang <insujang@umich.edu>
Maintainer-email: Insu Jang <insujang@umich.edu>
License:                                  Apache License
Project-URL: Homepages, https://cornstarch-org.github.io
Project-URL: Issues, https://github.com/cornstarch-org/Cornstarch/issues
Classifier: License :: OSI Approved :: Apache Software License
Classifier: Environment :: GPU :: NVIDIA CUDA
Classifier: Programming Language :: Python :: 3.10
Requires-Python: >=3.10
License-File: LICENSE.txt
Requires-Dist: torch>=2.5.0
Requires-Dist: triton<=3.1.0
Requires-Dist: transformers>=4.49.0
Requires-Dist: loguru
Requires-Dist: simple_parsing
Requires-Dist: datasets
Requires-Dist: tyro
Requires-Dist: flash-attn
Requires-Dist: numpy
Requires-Dist: tqdm
Requires-Dist: psutil
Requires-Dist: packaging
Requires-Dist: pre-commit
Requires-Dist: rich
Requires-Dist: click
Requires-Dist: fabric
Requires-Dist: contexttimer
Requires-Dist: ninja
Requires-Dist: safetensors
Requires-Dist: einops
Requires-Dist: pydantic
Requires-Dist: ray
Requires-Dist: sentencepiece
Requires-Dist: google
Requires-Dist: protobuf
Requires-Dist: peft
Requires-Dist: bitsandbytes>=0.39.0
Requires-Dist: rpyc==6.0.0
Requires-Dist: fastapi
Requires-Dist: uvicorn==0.29.0
Requires-Dist: galore_torch
Requires-Dist: diffusers==0.29.0
Requires-Dist: timm
Provides-Extra: dev
Requires-Dist: torch>=2.3.0; extra == "dev"
Requires-Dist: ruff; extra == "dev"
Requires-Dist: black>=23.0; extra == "dev"
Requires-Dist: isort>=5.12; extra == "dev"
Requires-Dist: pytest<=8.1; extra == "dev"
Requires-Dist: pytest-mock; extra == "dev"
Requires-Dist: expecttest; extra == "dev"
Requires-Dist: accelerate; extra == "dev"
Provides-Extra: docs
Requires-Dist: mkdocs; extra == "docs"
Requires-Dist: mkdocs-material; extra == "docs"
Requires-Dist: mkdocstrings; extra == "docs"
Provides-Extra: colossalai
Requires-Dist: colossalai==0.4.6; extra == "colossalai"
